abb_motion_program_exec/__init__.py
abb_motion_program_exec/abb_motion_program_exec_client.py
abb_motion_program_exec/abb_motion_program_exec_client_aio.py
abb_motion_program_exec/commands/__init__.py
abb_motion_program_exec/commands/command_base.py
abb_motion_program_exec/commands/commands.py
abb_motion_program_exec/commands/egm_commands.py
abb_motion_program_exec/commands/rapid_types.py
abb_motion_program_exec/commands/util.py
abb_motion_program_exec/robotraconteur/__init__.py
abb_motion_program_exec/robotraconteur/__main__.py
abb_motion_program_exec/robotraconteur/_motion_program_conv.py
abb_motion_program_exec/robotraconteur/abb_motion_program_exec_robotraconteur.py
abb_motion_program_exec/robotraconteur/experimental.abb_robot.motion_program.robdef
abb_motion_program_exec/robotraconteur/experimental.robotics.motion_program.robdef
abb_motion_program_exec-0.7.4.dist-info/LICENSE.txt
abb_motion_program_exec-0.7.4.dist-info/METADATA
abb_motion_program_exec-0.7.4.dist-info/WHEEL
abb_motion_program_exec-0.7.4.dist-info/entry_points.txt
abb_motion_program_exec-0.7.4.dist-info/top_level.txt
abb_motion_program_exec-0.7.4.dist-info/RECORD
