Metadata-Version: 2.1
Name: abb_motion_program_exec
Version: 0.7.4
Summary: Python package to execute motion commands on ABB robots and log results
Author-email: John Wason <wason@wasontech.com>
License: Apache-2.0
Project-URL: homepage, https://github.com/rpiRobotics/abb_motion_program_exec
Project-URL: documentation, https://abb-motion-program-exec.readthedocs.io/en/latest/
Project-URL: repository, https://github.com/rpiRobotics/abb_motion_program_exec
Requires-Python: >=3.6
License-File: LICENSE.txt
Requires-Dist: requests
Requires-Dist: numpy
Requires-Dist: abb-robot-client[aio]
Requires-Dist: dataclasses; python_version < "3.7"
Provides-Extra: robotraconteur
Requires-Dist: robotraconteur; extra == "robotraconteur"
Requires-Dist: robotraconteurcompanion; extra == "robotraconteur"
Requires-Dist: drekar-launch-process; extra == "robotraconteur"
Requires-Dist: robotraconteur-abstract-robot; extra == "robotraconteur"
Provides-Extra: test
Requires-Dist: pytest; extra == "test"
